openfigipy/__init__.py
openfigipy/_version.py
openfigipy/open_figi.py
openfigipy-0.1.6.dist-info/LICENSE
openfigipy-0.1.6.dist-info/METADATA
openfigipy-0.1.6.dist-info/WHEEL
openfigipy-0.1.6.dist-info/top_level.txt
openfigipy-0.1.6.dist-info/RECORD
