Metadata-Version: 2.1
Name: openfigipy
Version: 0.1.6
Summary: A python wrapper around the Open FIGI API that leverages pandas DataFrames
Home-page: https://github.com/ME-64/openfigipy
Author: ME-64
Author-email: milo_elliott@icloud.com
License: MIT
Keywords: API wrapper,Financial Reference Data,Open FIGI,openfigi,bloomberg,figi
Platform: UNKNOWN
Classifier: Development Status :: 3 - Alpha
Classifier: Intended Audience :: Developers
Classifier: License :: OSI Approved :: MIT License
Classifier: Programming Language :: Python :: 3.7
Classifier: Programming Language :: Python :: 3.8
Classifier: Programming Language :: Python :: 3.9
License-File: LICENSE
Requires-Dist: pandas
Requires-Dist: ratelimit
Requires-Dist: cachetools
Requires-Dist: requests
Provides-Extra: dev
